{
    "dashletDefTitle": "Changes",
    "valuePredefined": "ABAP Systems",
    "dashboardName": "Tai_Changes",
    "subtitle": "Autotest",
    "warningStatus": "assets/media/icons/checks/check-warning.svg",
    "okStatus": "assets/media/icons/checks/check-ok.svg",
    "critStatus": "assets/media/icons/checks/check-critical.svg",
    "warningCheck":"ols_runjs_auto",
    "okCheck":"AGENTALIVE",
    "critCheck": "ols_auto",
    "agentaliveOkResult": "Agent is known to be active since",
    "paramPredefined": "Predefined",
    "tableData": ["February", "30", "January", "204"],
    "currentMonth": "February",
    "previousMonth": "January"
}